flashembed/Embedder.py
flashembed/Embedder_test.py
flashembed/__init__.py
flashembed-0.0.2.dist-info/LICENSE
flashembed-0.0.2.dist-info/METADATA
flashembed-0.0.2.dist-info/WHEEL
flashembed-0.0.2.dist-info/top_level.txt
flashembed-0.0.2.dist-info/RECORD
