Metadata-Version: 2.1
Name: flashembed
Version: 0.0.2
Summary: Lightweight & Fast Python library to add low-footprint (all-MiniLM-* equivalent) multilingual retrievers to your RAG and Search & Retrieval pipelines.
Home-page: https://github.com/PrithivirajDamodaran/flashembed
Author: Prithivi Da
Author-email: 
License: Apache 2.0
Classifier: Programming Language :: Python :: 3
Classifier: License :: OSI Approved :: Apache Software License
Classifier: Operating System :: OS Independent
Requires-Python: >=3.6
License-File: LICENSE
Requires-Dist: tokenizers
Requires-Dist: onnxruntime
Requires-Dist: numpy
Requires-Dist: huggingface-hub
Requires-Dist: tqdm
Requires-Dist: llama-cpp-python (==0.2.67)
